{
    "URL_APP_ADMINISTRATIVO": "https://admin-dev.medicatel.red/",
    "USER_ADMINISTRATIVO": "pruebas@medicatel.red",
    "PASS_ADMINISTRATIVO": "MX8Rxnf5gHdf",
    "URL_APP_PROVEEDORES": "https://medicos-dev.redmedicatel.com/#/login",
    "USER_MEDICOPROVEEDORES": "vaniabarahona.ochoa@gmail.com",
    "PASS_MEDICOSPROVEEDORES": "M3d1cos-M3dicatel-2021",
    "NOMBRE_MEDICO": "Carlos Humberto García",
    "NOMBRE_MEDICO_LIQUIDACION": "Carlos Humberto",
    "URL_APP_PACIENTES": "https://pacientes-dev.medicatel.red/#/login",
    "URL_APP_INFORMATIVO": "https://informativo-dev.medicatel.red",
    "URL_APP_ACCOUNTING": "http://grupoandina.org/fenix2/auth/login",
    "USER_ACCOUNTING": "pruebas@medicatel.red",
    "PASS_ACCOUNTING": "MX8Rxnf5gHdf",
    "URL_MAILTRAP": "https://mailtrap.io/signin",
    "USER_MAILTRAP": "mhernandez@medicatel.red",
    "PASS_MAILTRAP": "Medicatel2022",
    "URL_EMPRESAS": "https://empresas-dev.medicatel.red/#/login",
    "URL_APP_SISA_ADMINISTRATIVO": "http://192.168.171.1:3000",
    "URL_APP_SISA_COTIZADOR": "http://192.168.171.1:3000",
    "URL_ASUGURAMECOTIZADOR": "https://staging.d21vlwmhu1266s.amplifyapp.com/#/home",
    "URL_ASUGURAMECR": "https://admin-dev.asegurame.cr/#/login",
    "PASS_ASUGURAMECR_ADMIN": "123456789"
}